pypomes_security/__init__.py
pypomes_security/access_data.py
pypomes_security/access_pomes.py
pypomes_security-0.2.2.dist-info/METADATA
pypomes_security-0.2.2.dist-info/WHEEL
pypomes_security-0.2.2.dist-info/licenses/LICENSE
pypomes_security-0.2.2.dist-info/RECORD
