Metadata-Version: 2.3
Name: pypomes_security
Version: 0.2.2
Summary: A collection of Python pomes, penyeach (security modules)
Project-URL: Homepage, https://github.com/TheWiseCoder/PyPomes-Security
Project-URL: Bug Tracker, https://github.com/TheWiseCoder/PyPomes-Security/issues
Author-email: GT Nunes <wisecoder01@gmail.com>
License-File: LICENSE
Classifier: License :: OSI Approved :: MIT License
Classifier: Operating System :: OS Independent
Classifier: Programming Language :: Python :: 3
Requires-Python: >=3.10
Requires-Dist: pip>=24.0
Requires-Dist: pypomes-core>=1.3.3
Requires-Dist: setuptools>=69.0.0
Requires-Dist: wheel>=0.41.0
